eeg_dementia_classification_MNet/MNet_1000.py
eeg_dementia_classification_MNet/_EnsembleMNet_1000.py
eeg_dementia_classification_MNet/_SingleMNet_1000.py
eeg_dementia_classification_MNet/__init__.py
eeg_dementia_classification_MNet/example.py
eeg_dementia_classification_MNet/utils.py
eeg_dementia_classification_MNet-1.4.1.dist-info/LICENSE
eeg_dementia_classification_MNet-1.4.1.dist-info/METADATA
eeg_dementia_classification_MNet-1.4.1.dist-info/WHEEL
eeg_dementia_classification_MNet-1.4.1.dist-info/top_level.txt
eeg_dementia_classification_MNet-1.4.1.dist-info/RECORD
