Metadata-Version: 2.1
Name: eeg-dementia-classification-MNet
Version: 1.4.1
Summary: Pretrained MNet model for classifying demetia subclasses (HV, AD, DLB, and iNPH)
Home-page: https://github.com/yanagisawa-lab/eeg-dementia-classification
Author: ywatanabe1989
Author-email: ywata1989@gmail.com
License: MIT
Keywords: dementia screening,mild cognitive impairment,Alzheimer's disease,AD,dementia with Lewy bodies,DLB,idiopathic normal-pressure hydrocephalus,iNPH,multiple centres
Classifier: Programming Language :: Python :: 3
Classifier: License :: OSI Approved :: MIT License
Requires-Python: >=3.0
License-File: LICENSE
Requires-Dist: torch
Requires-Dist: torchsummary
Requires-Dist: numpy
